risktools/_refineryLP.py
risktools/_cullenfrey.py
risktools/_swap.py
risktools/_charts.py
risktools/_multivariate.py
risktools/_pa.py
risktools/_sims.py
risktools/__init__.py
risktools/_morningstar.py
risktools/_main_functions.py
risktools/_sim_mp.py
risktools/extensions.so
risktools/data/cushing.json
risktools/data/eiaStocks.json
risktools/data/cma.json
risktools/data/tsQuotes.json
risktools/data/spot2futConvergence.json
risktools/data/crudeOil.json
risktools/data/ohlc.json
risktools/data/expiry_table.json
risktools/data/holidaysOil.json
risktools/data/fxfwd.json
risktools/data/tradeCycle.json
risktools/data/tradeprocess.json
risktools/data/eurodollar.json
risktools/data/steo.json
risktools/data/wtiSwap.json
risktools/data/usSwapCurves.json
risktools/data/__init__.py
risktools/data/usSwapCurvesPar.json
risktools/data/tradeHubs.json
risktools/data/tickers_eia.json
risktools/data/dflong.json
risktools/data/stocks.json
risktools/data/spot2futCurve.json
risktools/data/futuresRef.json
risktools/data/refineryLPdata.json
risktools/data/eiaStorageCap.json
risktools/data/dfwide.json
risktools/data/planets.json
risktools/data/__init__ - BAK.py
risktools/data/fizdiffs.json
risktools/pyx/sims.c
risktools-0.2.8.7.dist-info/top_level.txt
risktools-0.2.8.7.dist-info/RECORD
risktools-0.2.8.7.dist-info/LICENSE.txt
risktools-0.2.8.7.dist-info/METADATA
risktools-0.2.8.7.dist-info/WHEEL
