Metadata-Version: 2.1
Name: risktools
Version: 0.2.8.7
Summary: Python implementation of the R package RTL
Home-page: https://github.com/bbcho/risktools-dev
Author: Ben Cho
Author-email: ben.cho@gmail.com
License: gpl-3.0
Project-URL: Documentation, https://risktools.readthedocs.io/en/latest/
Keywords: RTL,Risk,Tools,Trading,Crude,Oil,Refinery,Refined Products,Products
Classifier: Development Status :: 4 - Beta
Classifier: License :: OSI Approved :: GNU General Public License v3 or later (GPLv3+)
Classifier: Programming Language :: Python :: 3
Classifier: Operating System :: OS Independent
Requires-Python: >=3.7
License-File: LICENSE.txt
Requires-Dist: pandas
Requires-Dist: numpy
Requires-Dist: matplotlib
Requires-Dist: plotly
Requires-Dist: quandl
Requires-Dist: scikit-learn
Requires-Dist: arch
Requires-Dist: scipy
Requires-Dist: statsmodels
Requires-Dist: seaborn
Requires-Dist: pandas-datareader
